chip/ChipUtility.py
chip/clusters/CHIPClusters.py
chip/clusters/ClusterObjects.py
chip/clusters/Objects.py
chip/clusters/TestObjects.py
chip/clusters/Types.py
chip/clusters/enum.py
chip/tlv/__init__.py
chip/tlv/tlvlist.py
ks_chip_clusters-2024.7.1.dist-info/LICENSE
ks_chip_clusters-2024.7.1.dist-info/METADATA
ks_chip_clusters-2024.7.1.dist-info/WHEEL
ks_chip_clusters-2024.7.1.dist-info/top_level.txt
ks_chip_clusters-2024.7.1.dist-info/RECORD
