Metadata-Version: 2.1
Name: ks-chip-clusters
Version: 2024.7.1
Summary: Python-base APIs and tools for CHIP.
Home-page: https://github.com/project-chip/connectedhomeip
License: Apache
Classifier: Intended Audience :: Developers
Classifier: License :: OSI Approved :: Apache Software License
Classifier: Programming Language :: Python :: 3.7
Classifier: Programming Language :: Python :: 3.8
Classifier: Programming Language :: Python :: 3.9
Classifier: Programming Language :: Python :: 3.10
Classifier: Programming Language :: Python :: 3.11
Classifier: Programming Language :: Python :: 3.12
Requires-Python: >=3.7
License-File: LICENSE
Requires-Dist: dacite
Requires-Dist: aenum
